faroc/FaRoC_ascii_art
faroc/__init__.py
faroc/faroc.py
faroc/fanuc_alarm_codes/fanuc_alarm_codes_api.json
faroc/fanuc_alarm_codes/fanuc_alarm_codes_manual.json
faroc/fanuc_alarm_codes/fanuc_error_tools.py
faroc/fanuc_alarm_codes/table_facility_codes.csv
faroc/fanuc_alarm_codes/table_facility_codes_by_name.json
faroc/fanuc_alarm_codes/table_facility_codes_by_number.json
faroc-0.7.5.dist-info/LICENSE
faroc-0.7.5.dist-info/METADATA
faroc-0.7.5.dist-info/WHEEL
faroc-0.7.5.dist-info/entry_points.txt
faroc-0.7.5.dist-info/top_level.txt
faroc-0.7.5.dist-info/RECORD
