Metadata-Version: 2.1
Name: faroc
Version: 0.7.5
Summary: FaRoC (Fanuc Robot Control): a Python package for FANUC industrial robots
Author-email: Wael Hojak <w.hojak@tutamail.com>
License: Apache License
Project-URL: Homepage, https://codeberg.org/hojak/faroc
Project-URL: Source, https://codeberg.org/hojak/faroc
Project-URL: Bug Reports, https://codeberg.org/hojak/faroc/issues
Keywords: fanuc,robot,development
Classifier: License :: OSI Approved :: Apache Software License
Classifier: Programming Language :: Python :: 3.6
Classifier: Operating System :: OS Independent
Classifier: Framework :: Robot Framework
Classifier: Development Status :: 5 - Production/Stable
Classifier: Intended Audience :: Developers
Classifier: Intended Audience :: Education
Classifier: Intended Audience :: Science/Research
Requires-Python: >=3.6
License-File: LICENSE
Provides-Extra: dev
Requires-Dist: pytest (>=7.0) ; extra == 'dev'
Requires-Dist: twine (>=4.0.2) ; extra == 'dev'
